libarchive/__init__.py
libarchive/exception.py
libarchive/library.py
libarchive/public.py
libarchive/adapters/__init__.py
libarchive/adapters/archive_entry.py
libarchive/adapters/archive_read.py
libarchive/adapters/archive_read_append_filter.py
libarchive/adapters/archive_read_set_format.py
libarchive/adapters/archive_read_support_filter_all.py
libarchive/adapters/archive_read_support_format_all.py
libarchive/adapters/archive_write.py
libarchive/adapters/archive_write_add_filter.py
libarchive/adapters/archive_write_set_format.py
libarchive/calls/__init__.py
libarchive/calls/archive_entry.py
libarchive/calls/archive_general.py
libarchive/calls/archive_read.py
libarchive/calls/archive_read_append_filter.py
libarchive/calls/archive_read_set_format.py
libarchive/calls/archive_read_support_filter_all.py
libarchive/calls/archive_read_support_format_all.py
libarchive/calls/archive_write.py
libarchive/calls/archive_write_add_filter.py
libarchive/calls/archive_write_set_format.py
libarchive/constants/__init__.py
libarchive/constants/archive.py
libarchive/constants/archive_entry.py
libarchive/resources/README.rst
libarchive/resources/requirements.txt
libarchive/types/__init__.py
libarchive/types/archive.py
libarchive/types/archive_entry.py
libarchive-0.4.3.dist-info/DESCRIPTION.rst
libarchive-0.4.3.dist-info/METADATA
libarchive-0.4.3.dist-info/metadata.json
libarchive-0.4.3.dist-info/RECORD
libarchive-0.4.3.dist-info/top_level.txt
libarchive-0.4.3.dist-info/WHEEL
