Metadata-Version: 2.0
Name: libarchive
Version: 0.4.3
Summary: Python adapter for universal, libarchive-based archive access.
Home-page: https://github.com/dsoprea/PyEasyArchive
Author: Dustin Oprea
Author-email: myselfasunder@gmail.com
License: GPL 2
Keywords: archive libarchive 7z tar bz2 zip gz
Platform: UNKNOWN
Requires-Dist: nose
